<?xml version="1.0"?>
<!DOCTYPE hibernate-mapping PUBLIC "-//Hibernate/Hibernate Mapping DTD 3.0//EN"
"http://www.hibernate.org/dtd/hibernate-mapping-3.0.dtd">
<!-- Generated 06/11/2015 11:03:54 AM by Hibernate Tools 4.3.1 -->
<hibernate-mapping>
    <class name="pe.gob.mef.gescon.hibernate.domain.Mtalerta" table="MTALERTA" schema="GESCON3" optimistic-lock="version">
        <id name="nalertaid" type="big_decimal">
            <column name="NALERTAID" precision="22" scale="0" />
            <generator class="assigned" />
        </id>
        <many-to-one name="mtparametro" class="pe.gob.mef.gescon.hibernate.domain.Mtparametro" fetch="select">
            <column name="NPARAMETROID" precision="22" scale="0" not-null="true" />
        </many-to-one>
        <property name="vnombre" type="string">
            <column name="VNOMBRE" length="25" />
        </property>
        <property name="vdescripcion" type="string">
            <column name="VDESCRIPCION" length="400" />
        </property>
        <property name="nactivo" type="big_decimal">
            <column name="NACTIVO" precision="22" scale="0" />
        </property>
        <property name="nuseraplica" type="big_decimal">
            <column name="NUSERAPLICA" precision="22" scale="0" />
        </property>
        <property name="dfechini" type="date">
            <column name="DFECHINI" length="7" />
        </property>
        <property name="dfechfin" type="date">
            <column name="DFECHFIN" length="7" />
        </property>
        <property name="vcondicion1" type="string">
            <column name="VCONDICION1" length="20" />
        </property>
        <property name="vcondicion2" type="string">
            <column name="VCONDICION2" length="20" />
        </property>
        <property name="nvalor1" type="big_decimal">
            <column name="NVALOR1" precision="22" scale="0" />
        </property>
        <property name="nvalor2" type="big_decimal">
            <column name="NVALOR2" precision="22" scale="0" />
        </property>
        <property name="ntipo1" type="big_decimal">
            <column name="NTIPO1" precision="22" scale="0" />
        </property>
        <property name="ntipo2" type="big_decimal">
            <column name="NTIPO2" precision="22" scale="0" />
        </property>
        <property name="vusuariocreacion" type="string">
            <column name="VUSUARIOCREACION" length="25" />
        </property>
        <property name="vusuariomodificacion" type="string">
            <column name="VUSUARIOMODIFICACION" length="25" />
        </property>
        <property name="dfechacreacion" type="timestamp">
            <column name="DFECHACREACION" />
        </property>
        <property name="dfechamodificacion" type="timestamp">
            <column name="DFECHAMODIFICACION" />
        </property>
    </class>
</hibernate-mapping>
